{
    "packages": {
        "numiko/slice-media-embed-recipe": [
            {
                "name": "numiko/slice-media-embed-recipe",
                "version": "1.0.0",
                "version_normalized": "1.0.0.0",
                "source": {
                    "type": "git",
                    "url": "git@bitbucket.org:numiko/slice-media-embed-recipe.git",
                    "reference": "bed3246ca9ab9219011561f2671282bbcffb84a0"
                },
                "dist": {
                    "type": "tar",
                    "url": "https://numiko.github.io/packagist/dist/numiko/slice-media-embed-recipe/numiko-slice-media-embed-recipe-1.0.0-0be166.tar",
                    "reference": "bed3246ca9ab9219011561f2671282bbcffb84a0",
                    "shasum": "6355392c9878c3f183956c5703a4727baaa853c8"
                },
                "time": "2025-01-09T16:02:37+00:00",
                "type": "drupal-recipe",
                "license": [
                    "GPL-2.0-or-later"
                ],
                "description": "A Drupal recipe for new Media Embed recipe paragraph type"
            },
            {
                "name": "numiko/slice-media-embed-recipe",
                "version": "1.0.1",
                "version_normalized": "1.0.1.0",
                "source": {
                    "type": "git",
                    "url": "git@bitbucket.org:numiko/slice-media-embed-recipe.git",
                    "reference": "e033ee44f0b9301bd813f6a8ea72d67f82596e20"
                },
                "dist": {
                    "type": "tar",
                    "url": "https://numiko.github.io/packagist/dist/numiko/slice-media-embed-recipe/numiko-slice-media-embed-recipe-1.0.1-ad6417.tar",
                    "reference": "e033ee44f0b9301bd813f6a8ea72d67f82596e20",
                    "shasum": "64a6190d70aabb8a17153602cfa0f82e691a12a0"
                },
                "time": "2025-01-09T16:25:25+00:00",
                "type": "drupal-recipe",
                "license": [
                    "GPL-2.0-or-later"
                ],
                "description": "A Drupal recipe for new Media Embed recipe paragraph type"
            },
            {
                "name": "numiko/slice-media-embed-recipe",
                "version": "1.0.2",
                "version_normalized": "1.0.2.0",
                "source": {
                    "type": "git",
                    "url": "git@bitbucket.org:numiko/slice-media-embed-recipe.git",
                    "reference": "203bfabed971d53088b0f9aea619d621d4d96aac"
                },
                "dist": {
                    "type": "tar",
                    "url": "https://numiko.github.io/packagist/dist/numiko/slice-media-embed-recipe/numiko-slice-media-embed-recipe-1.0.2-ecc763.tar",
                    "reference": "203bfabed971d53088b0f9aea619d621d4d96aac",
                    "shasum": "869d527ee2ad0df29bd9d4182cbb0fa295821434"
                },
                "time": "2025-01-15T11:49:46+00:00",
                "type": "drupal-recipe",
                "license": [
                    "GPL-2.0-or-later"
                ],
                "description": "A Drupal recipe for new Media Embed recipe paragraph type"
            }
        ]
    }
}
