{
    "packages": {
        "numiko/slice-author-name-recipe": [
            {
                "name": "numiko/slice-author-name-recipe",
                "version": "1.0.0",
                "version_normalized": "1.0.0.0",
                "source": {
                    "type": "git",
                    "url": "git@bitbucket.org:numiko/slice-author-name-recipe.git",
                    "reference": "85345a0f92b39cf22d1ec22abf876471f8a65792"
                },
                "dist": {
                    "type": "tar",
                    "url": "https://numiko.github.io/packagist/dist/numiko/slice-author-name-recipe/numiko-slice-author-name-recipe-1.0.0-9677bf.tar",
                    "reference": "85345a0f92b39cf22d1ec22abf876471f8a65792",
                    "shasum": "9c3683b85ec5d3d9a1dd524104bb5089b1d01b30"
                },
                "require": {
                    "drupal/core-recommended": "^10.3"
                },
                "time": "2025-01-09T13:11:07+00:00",
                "type": "drupal-recipe",
                "license": [
                    "GPL-2.0-or-later"
                ],
                "description": "A Drupal recipe for new Slice Author Name paragraph type"
            },
            {
                "name": "numiko/slice-author-name-recipe",
                "version": "1.0.1",
                "version_normalized": "1.0.1.0",
                "source": {
                    "type": "git",
                    "url": "git@bitbucket.org:numiko/slice-author-name-recipe.git",
                    "reference": "cfbb2a6e80e4363153ee77a0deb80fe6d0aa393e"
                },
                "dist": {
                    "type": "tar",
                    "url": "https://numiko.github.io/packagist/dist/numiko/slice-author-name-recipe/numiko-slice-author-name-recipe-1.0.1-b5dab3.tar",
                    "reference": "cfbb2a6e80e4363153ee77a0deb80fe6d0aa393e",
                    "shasum": "b9bf8b41a173797fa39fd7537b32d79bf6ed9c68"
                },
                "require": {
                    "drupal/core-recommended": "^10.3"
                },
                "time": "2025-01-09T13:35:33+00:00",
                "type": "drupal-recipe",
                "license": [
                    "GPL-2.0-or-later"
                ],
                "description": "A Drupal recipe for new Slice Author Name paragraph type"
            },
            {
                "name": "numiko/slice-author-name-recipe",
                "version": "1.0.2",
                "version_normalized": "1.0.2.0",
                "source": {
                    "type": "git",
                    "url": "git@bitbucket.org:numiko/slice-author-name-recipe.git",
                    "reference": "eb682b91a38913c3ed46e72dcbf096f344deaf1f"
                },
                "dist": {
                    "type": "tar",
                    "url": "https://numiko.github.io/packagist/dist/numiko/slice-author-name-recipe/numiko-slice-author-name-recipe-1.0.2-91418c.tar",
                    "reference": "eb682b91a38913c3ed46e72dcbf096f344deaf1f",
                    "shasum": "bbcd24963182de5672064744e2dbaace47ed80ff"
                },
                "time": "2025-01-09T13:43:33+00:00",
                "type": "drupal-recipe",
                "license": [
                    "GPL-2.0-or-later"
                ],
                "description": "A Drupal recipe for new Slice Author Name paragraph type"
            },
            {
                "name": "numiko/slice-author-name-recipe",
                "version": "1.0.3",
                "version_normalized": "1.0.3.0",
                "source": {
                    "type": "git",
                    "url": "git@bitbucket.org:numiko/slice-author-name-recipe.git",
                    "reference": "472a4577570a076015b808434db0416c532d9cc2"
                },
                "dist": {
                    "type": "tar",
                    "url": "https://numiko.github.io/packagist/dist/numiko/slice-author-name-recipe/numiko-slice-author-name-recipe-1.0.3-4c1c3c.tar",
                    "reference": "472a4577570a076015b808434db0416c532d9cc2",
                    "shasum": "6f05a7c9975cf8651091889a6570098315b4fdd1"
                },
                "time": "2025-01-09T14:33:18+00:00",
                "type": "drupal-recipe",
                "license": [
                    "GPL-2.0-or-later"
                ],
                "description": "A Drupal recipe for new Slice Author Name paragraph type"
            }
        ]
    }
}
