{
    "packages": {
        "numiko/time_field_select": [
            {
                "name": "numiko/time_field_select",
                "version": "1.0.0",
                "version_normalized": "1.0.0.0",
                "source": {
                    "type": "git",
                    "url": "git@bitbucket.org:numiko/time-field-select.git",
                    "reference": "5692c1dbb935028e9c5774a7cf8c8c4e1eb2086f"
                },
                "dist": {
                    "type": "tar",
                    "url": "https://numiko.github.io/packagist/dist/numiko/time_field_select/numiko-time_field_select-1.0.0-cb2c53.tar",
                    "reference": "5692c1dbb935028e9c5774a7cf8c8c4e1eb2086f",
                    "shasum": "340409b06ff95beae4e24b8c5a866206714fa631"
                },
                "time": "2023-02-01T17:25:15+00:00",
                "type": "drupal-module",
                "license": [
                    "GPL-2.0+"
                ],
                "description": "Field widget for allowing a time select on a string field",
                "keywords": [
                    "Drupal"
                ]
            },
            {
                "name": "numiko/time_field_select",
                "version": "1.1.0-beta1",
                "version_normalized": "1.1.0.0-beta1",
                "source": {
                    "type": "git",
                    "url": "git@bitbucket.org:numiko/time-field-select.git",
                    "reference": "68a933bade732eec87d1c97aa400ca26198f7dd1"
                },
                "dist": {
                    "type": "tar",
                    "url": "https://numiko.github.io/packagist/dist/numiko/time_field_select/numiko-time_field_select-1.1.0-beta1-0a02e3.tar",
                    "reference": "68a933bade732eec87d1c97aa400ca26198f7dd1",
                    "shasum": "4073755bdfad39ae99e0905974d851091fe3a8c7"
                },
                "time": "2025-07-29T14:33:45+00:00",
                "type": "drupal-module",
                "license": [
                    "GPL-2.0+"
                ],
                "description": "Field widget for allowing a time select on a string field",
                "keywords": [
                    "Drupal"
                ]
            }
        ]
    }
}
